LICENSE
MANIFEST.in
README.rst
setup.cfg
setup.py
drf_swaggify.egg-info/PKG-INFO
drf_swaggify.egg-info/SOURCES.txt
drf_swaggify.egg-info/dependency_links.txt
drf_swaggify.egg-info/top_level.txt
swaggify/__init__.py