Metadata-Version: 1.1
Name: drf-swaggify
Version: 0.1.2
Summary: A Django Rest Framework API documentation generator.
Home-page: https://github.com/stingpan/drf-swaggify
Author: Christine Pan
Author-email: pan.christine@gmail.com
License: BSD
Platform: UNKNOWN
Classifier: Development Status :: 2 - Pre-Alpha
Classifier: Environment :: Web Environment
Classifier: Framework :: Django
Classifier: Intended Audience :: Developers
Classifier: License :: OSI Approved :: BSD License
Classifier: Operating System :: OS Independent
Classifier: Natural Language :: English
Classifier: Programming Language :: Python :: 2.7
Classifier: Topic :: Internet :: WWW/HTTP
